adtsdk/__init__.py
adtsdk/cli.py
adtsdk/constants.py
adtsdk/core.py
adtsdk/datasource.py
adtsdk/exceptions.py
adtsdk/upload.py
adt_sdk-1.0.0.dist-info/entry_points.txt
adt_sdk-1.0.0.dist-info/WHEEL
adt_sdk-1.0.0.dist-info/METADATA
adt_sdk-1.0.0.dist-info/RECORD
