Metadata-Version: 2.1
Name: adt-sdk
Version: 1.0.0
Summary: The package provides ADT SDK for uploading data with ADT Upload API
Home-page: https://github.com/datamole-ai/adt-sdk
Author: Datamole ADT
Author-email: adt@datamole.ai
Requires-Python: >=3.7.9,<3.11
Classifier: Programming Language :: Python :: 3
Classifier: Programming Language :: Python :: 3.8
Classifier: Programming Language :: Python :: 3.9
Classifier: Programming Language :: Python :: 3.10
Requires-Dist: pandas (>=1.3.5,<1.4.0)
Requires-Dist: requests (>=2.28.1,<3.0.0)
Project-URL: Repository, https://github.com/datamole-ai/adt-sdk
